{
    "proplibs_new": [
        {
            "library": "Bush.tara",
            "version": 2
        },
        {
            "library": "CityBuilds.tara",
            "version": 2
        },
        {
            "library": "Cliffs.tara",
            "version": 2
        },
        {
            "library": "ConcreteTiles.tara",
            "version": 2
        },
        {
            "library": "GrassTiles.tara",
            "version": 2
        },
        {
            "library": "NuBu1.tara",
            "version": 2
        },
        {
            "library": "NuBu10.tara",
            "version": 2
        },
        {
            "library": "NuBu14.tara",
            "version": 2
        },
        {
            "library": "NuBu2.tara",
            "version": 2
        },
        {
            "library": "NuBu3.tara",
            "version": 2
        },
        {
            "library": "NuBu4.tara",
            "version": 2
        },
        {
            "library": "NuBu5.tara",
            "version": 2
        },
        {
            "library": "NuBu8.tara",
            "version": 2
        },
        {
            "library": "NuBu9.tara",
            "version": 2
        },
        {
            "library": "Promotion.tara",
            "version": 3
        },
        {
            "library": "SlopesRises.tara",
            "version": 2
        }
    ]
}